{
  "naam": "Demo Klant B.V.",
  "logo": "🌊",
  "accent_kleur": "#10b981",
  "groei_team": {
    "pakket": "Pro",
    "sinds": "2026-01-15",
    "status": "actief",
    "contact_frequentie": "wekelijks",
    "laatste_checkin": "2026-05-05",
    "volgende_checkin": "2026-05-12",
    "health_score": 87,
    "prijs": {
      "maand": 2499,
      "setup": 2500,
      "jaar": 24990,
      "valuta": "EUR"
    },
    "workflows": [
      {"naam": "Lead opvolging", "type": "lead", "actief": true, "items_verwerkt": 847, "opvolgmomenten": 3, "laatste_actie": "2026-05-03", "status": "groen"},
      {"naam": "Klantinteractie", "type": "support", "actief": true, "items_verwerkt": 320, "opvolgmomenten": 5, "laatste_actie": "2026-05-03", "status": "groen"},
      {"naam": "Facturatie", "type": "finance", "actief": true, "items_verwerkt": 180, "opvolgmomenten": 2, "laatste_actie": "2026-05-02", "status": "groen"},
      {"naam": "Dataverwerking", "type": "data", "actief": true, "items_verwerkt": 260, "opvolgmomenten": 4, "laatste_actie": "2026-05-03", "status": "groen"},
      {"naam": "Rapportage", "type": "reporting", "actief": true, "items_verwerkt": 87, "opvolgmomenten": 1, "laatste_actie": "2026-05-01", "status": "oranje"}
    ],
    "hitl_samenvatting": {
      "deze_maand_goedgekeurd": 152,
      "deze_maand_geweigerd": 3,
      "wachttijd_gemiddeld": "2.4 uur"
    },
    "kpi_koppeling": {
      "opvolging_binnen_24u": "Gem. responstijd",
      "gemiste_kansen": "Verwerkte items",
      "conversie": "Nauwkeurigheid"
    },
    "checkin_historie": [
      {"datum": "2026-05-05", "type": "wekelijkse check-in", "notities": "Alles op koers. Facturatie-automatisering loopt soepel.", "status": "groen"},
      {"datum": "2026-04-28", "type": "wekelijkse check-in", "notities": "Lichte toename in support tickets, team ingepland.", "status": "groen"},
      {"datum": "2026-04-21", "type": "wekelijkse check-in", "notities": "Lead opvolging geoptimaliseerd, responstijd omlaag.", "status": "groen"},
      {"datum": "2026-04-14", "type": "wekelijkse check-in", "notities": "Nieuwe KPI-koppeling ingesteld voor rapportage.", "status": "oranje"}
    ]
  },
  "periodes": {
    "Mei 2026": {
      "laatste_update": "2026-05-03",
      "kpis": {
        "Verwerkte items": {"waarde": 847, "doel": 800, "eenheid": "items", "status": "groen", "trend": "+8.3% vs vorige maand"},
        "Gem. responstijd": {"waarde": 2.3, "doel": 3.0, "eenheid": "seconden", "status": "groen", "trend": "-0.4s vs vorige maand"},
        "Nauwkeurigheid": {"waarde": 96, "doel": 95, "eenheid": "%", "status": "groen", "trend": "+1% vs vorige maand"},
        "Uptime": {"waarde": 99.8, "doel": 99.0, "eenheid": "%", "status": "groen", "trend": "Gelijk"},
        "HITL-ratio": {"waarde": 18, "doel": 20, "eenheid": "%", "status": "groen", "trend": "-2% vs vorige maand"},
        "Kostenbesparing": {"waarde": 3420, "doel": 3000, "eenheid": "euro", "status": "groen", "trend": "+€420 vs vorige maand"}
      },
      "grafieken": {
        "verwerkte_items_per_dag": {"titel": "Verwerkte items per dag", "labels": ["Ma","Di","Wo","Do","Vr","Za","Zo"], "waarden": [145,162,158,171,149,42,20], "doel": 114},
        "responstijd_per_dag": {"titel": "Gemiddelde responstijd per dag (s)", "labels": ["Ma","Di","Wo","Do","Vr","Za","Zo"], "waarden": [2.1,2.4,2.3,2.0,2.5,2.8,3.1], "doel": 3.0},
        "hitl_trend": {"titel": "HITL-ratio per week", "labels": ["W1","W2","W3","W4","W5"], "waarden": [24,22,20,19,18], "doel": 20}
      },
      "bottleneck": {"actief": false, "tekst": "Geen knelpunten deze week. Alle processen draaien binnen de gestelde doelen.", "prioriteit": "laag"},
      "hitl_detail": {
        "totaal_acties": 847, "menselijke_check": 152, "geautomatiseerd": 695, "bespaarde_uren": 18.5,
        "categorieen": {
          "Klantinteractie": {"totaal": 320, "hitl": 45, "percentage": 14},
          "Facturatie": {"totaal": 180, "hitl": 30, "percentage": 17},
          "Dataverwerking": {"totaal": 260, "hitl": 52, "percentage": 20},
          "Rapportage": {"totaal": 87, "hitl": 25, "percentage": 29}
        }
      },
      "kosten_besparing": 3420,
      "doelen_vorige_maand": {"verwerkte_items": 782, "responstijd": 2.7, "nauwkeurigheid": 95, "hitl_ratio": 20, "kosten_besparing": 3000}
    },
    "April 2026": {
      "laatste_update": "2026-04-05",
      "kpis": {
        "Verwerkte items": {"waarde": 782, "doel": 750, "eenheid": "items", "status": "groen", "trend": "+5.1% vs vorige maand"},
        "Gem. responstijd": {"waarde": 2.7, "doel": 3.0, "eenheid": "seconden", "status": "groen", "trend": "+0.1s vs vorige maand"},
        "Nauwkeurigheid": {"waarde": 95, "doel": 95, "eenheid": "%", "status": "groen", "trend": "Gelijk"},
        "Uptime": {"waarde": 99.5, "doel": 99.0, "eenheid": "%", "status": "groen", "trend": "-0.2% vs vorige maand"},
        "HITL-ratio": {"waarde": 20, "doel": 20, "eenheid": "%", "status": "groen", "trend": "Gelijk"},
        "Kostenbesparing": {"waarde": 3000, "doel": 2800, "eenheid": "euro", "status": "groen", "trend": "+€200 vs vorige maand"}
      },
      "grafieken": {
        "verwerkte_items_per_dag": {"titel": "Verwerkte items per dag", "labels": ["Ma","Di","Wo","Do","Vr","Za","Zo"], "waarden": [132,148,151,143,138,35,18], "doel": 107},
        "responstijd_per_dag": {"titel": "Gemiddelde responstijd per dag (s)", "labels": ["Ma","Di","Wo","Do","Vr","Za","Zo"], "waarden": [2.5,2.6,2.8,2.4,2.7,3.0,3.2], "doel": 3.0},
        "hitl_trend": {"titel": "HITL-ratio per week", "labels": ["W1","W2","W3","W4"], "waarden": [26,24,22,20], "doel": 20}
      },
      "bottleneck": {"actief": true, "tekst": "Lichte stijging in responstijd aan het einde van de maand. Mogelijke capaciteitsuitbreiding nodig.", "prioriteit": "medium"},
      "hitl_detail": {
        "totaal_acties": 782, "menselijke_check": 156, "geautomatiseerd": 626, "bespaarde_uren": 16.2,
        "categorieen": {
          "Klantinteractie": {"totaal": 290, "hitl": 52, "percentage": 18},
          "Facturatie": {"totaal": 165, "hitl": 33, "percentage": 20},
          "Dataverwerking": {"totaal": 240, "hitl": 48, "percentage": 20},
          "Rapportage": {"totaal": 87, "hitl": 23, "percentage": 26}
        }
      },
      "kosten_besparing": 3000,
      "doelen_vorige_maand": {"verwerkte_items": 744, "responstijd": 2.6, "nauwkeurigheid": 94, "hitl_ratio": 22, "kosten_besparing": 2800}
    }
  }
}
